.gitignore
LICENSE
MANIFEST.in
README.md
requirements.txt
setup.py
bin/isoclassify
examples/direct.ipynb
examples/example.csv
examples/grid.ipynb
isoclassify/__init__.py
isoclassify/extinction.py
isoclassify/isoclassify.py
isoclassify/pipeline.py
isoclassify.egg-info/PKG-INFO
isoclassify.egg-info/SOURCES.txt
isoclassify.egg-info/dependency_links.txt
isoclassify.egg-info/entry_points.txt
isoclassify.egg-info/requires.txt
isoclassify.egg-info/top_level.txt
isoclassify/data/distance-samples-green19.txt
isoclassify/data/extinction-vector-cardelli-iso.txt
isoclassify/data/extinction-vector-green19-iso.txt
isoclassify/data/extinction-vector-schlafly11-iso.txt
isoclassify/data/extinction-vector-schlafly16-iso.txt
isoclassify/direct/__init__.py
isoclassify/direct/asfgrid.py
isoclassify/direct/bprp-solar-mist.txt
isoclassify/direct/classify.py
isoclassify/direct/getmesabc.py
isoclassify/direct/jk-solar-mist.txt
isoclassify/grid/__init__.py
isoclassify/grid/classify.py
isoclassify/grid/example-bc.ipynb
isoclassify/grid/match.py
isoclassify/grid/pdf.py
isoclassify/grid/plot.py
isoclassify/grid/priors.py
isoclassify/grid/temp
scripts/huber17/apokasc_direct.py
scripts/huber17/apokasc_grid.py
scripts/huber17/ini
scripts/huber17/tgas_combined_obs.txt
scripts/singlestar/isoclassify-script
scripts/singlestar/makeinput.py
scripts/singlestar/out-direct.py
scripts/singlestar/out-grid.py