Metadata-Version: 1.0
Name: isoclassify
Version: 1.4
Summary: Python codes to perform stellar classifications given any set of input observables.
Home-page: UNKNOWN
Author: Daniel Huber
Author-email: UNKNOWN
License: UNKNOWN
Platform: UNKNOWN
